nflreadpy/__init__.py
nflreadpy/cache.py
nflreadpy/config.py
nflreadpy/downloader.py
nflreadpy/load_combine.py
nflreadpy/load_contracts.py
nflreadpy/load_depth_charts.py
nflreadpy/load_draft_picks.py
nflreadpy/load_ffverse.py
nflreadpy/load_ftn_charting.py
nflreadpy/load_injuries.py
nflreadpy/load_nextgen_stats.py
nflreadpy/load_officials.py
nflreadpy/load_participation.py
nflreadpy/load_pbp.py
nflreadpy/load_players.py
nflreadpy/load_rosters.py
nflreadpy/load_rosters_weekly.py
nflreadpy/load_schedules.py
nflreadpy/load_snap_counts.py
nflreadpy/load_stats.py
nflreadpy/load_teams.py
nflreadpy/load_trades.py
nflreadpy/utils_date.py
nflreadpy-0.1.3.dist-info/WHEEL
nflreadpy-0.1.3.dist-info/METADATA
nflreadpy-0.1.3.dist-info/RECORD
