Metadata-Version: 2.4
Name: nflreadpy
Version: 0.1.3
Summary: A Python package for downloading NFL data from nflverse repositories
Keywords: nfl,football,sports,data,analytics
Author: Tan Ho
Author-email: Tan Ho <nflverse@tanho.ca>
License-Expression: MIT
Classifier: Development Status :: 4 - Beta
Classifier: Intended Audience :: Science/Research
Classifier: License :: OSI Approved :: MIT License
Classifier: Programming Language :: Python :: 3
Classifier: Programming Language :: Python :: 3.10
Classifier: Programming Language :: Python :: 3.11
Classifier: Programming Language :: Python :: 3.12
Classifier: Programming Language :: Python :: 3.13
Classifier: Topic :: Scientific/Engineering :: Information Analysis
Classifier: Topic :: Software Development :: Libraries :: Python Modules
Requires-Dist: requests>=2.28.0
Requires-Dist: polars>=0.20.0
Requires-Dist: platformdirs>=3.0.0
Requires-Dist: tqdm>=4.64.0
Requires-Dist: pydantic>=2.0.0
Requires-Dist: pydantic-settings>=2.0.0
Requires-Dist: pandas>=1.5.0 ; extra == 'pandas'
Requires-Python: >=3.10
Project-URL: Documentation, https://nflreadpy.nflverse.com
Project-URL: Homepage, https://github.com/nflverse/nflreadpy
Project-URL: Issues, https://github.com/nflverse/nflreadpy/issues
Project-URL: Repository, https://github.com/nflverse/nflreadpy
Provides-Extra: pandas
